{
  "kind": "singleType",
  "collectionName": "careers",
  "info": {
    "singularName": "career",
    "pluralName": "careers",
    "displayName": "Career",
    "description": ""
  },
  "options": {
    "draftAndPublish": true
  },
  "pluginOptions": {
    "i18n": {
      "localized": true
    }
  },
  "attributes": {
    "heroSection": {
      "type": "component",
      "repeatable": false,
      "component": "shared.hero",
      "pluginOptions": {
        "i18n": {
          "localized": true
        }
      }
    },
    "challengeSection": {
      "type": "component",
      "repeatable": false,
      "component": "shared.hero",
      "pluginOptions": {
        "i18n": {
          "localized": true
        }
      }
    },
    "guideSection": {
      "type": "dynamiczone",
      "components": [
        "shared.teck-stack",
        "core.button"
      ],
      "pluginOptions": {
        "i18n": {
          "localized": true
        }
      }
    },
    "jobsSection": {
      "type": "component",
      "repeatable": false,
      "component": "shared.callout",
      "pluginOptions": {
        "i18n": {
          "localized": true
        }
      }
    },
    "planSection": {
      "type": "component",
      "repeatable": false,
      "component": "shared.hero",
      "pluginOptions": {
        "i18n": {
          "localized": true
        }
      }
    },
    "trendingSection": {
      "type": "component",
      "repeatable": false,
      "component": "core.header",
      "pluginOptions": {
        "i18n": {
          "localized": true
        }
      }
    }
  }
}
