{
  "kind": "singleType",
  "collectionName": "pricings",
  "info": {
    "singularName": "pricing",
    "pluralName": "pricings",
    "displayName": "Pricing",
    "description": ""
  },
  "options": {
    "draftAndPublish": true
  },
  "pluginOptions": {
    "i18n": {
      "localized": true
    }
  },
  "attributes": {
    "heroSection": {
      "type": "component",
      "repeatable": false,
      "component": "shared.hero"
    },
    "problemSection": {
      "type": "component",
      "repeatable": false,
      "component": "shared.callout",
      "pluginOptions": {
        "i18n": {
          "localized": true
        }
      }
    },
    "planSection": {
      "type": "dynamiczone",
      "components": [
        "shared.plan-feature",
        "shared.callout"
      ]
    },
    "testimonialSection": {
      "type": "component",
      "repeatable": false,
      "component": "shared.feature"
    },
    "faqSection": {
      "type": "component",
      "repeatable": false,
      "component": "shared.teck-stack"
    },
    "ctaSection": {
      "type": "component",
      "repeatable": false,
      "component": "shared.hero"
    },
    "guideSection": {
      "type": "component",
      "repeatable": false,
      "component": "shared.hero"
    }
  }
}
